yomari/__init__.py
yomari-0.0.1.dist-info/LICENSE
yomari-0.0.1.dist-info/METADATA
yomari-0.0.1.dist-info/WHEEL
yomari-0.0.1.dist-info/top_level.txt
yomari-0.0.1.dist-info/RECORD
