Metadata-Version: 2.1
Name: yomari
Version: 0.0.1
Summary: Yet Another Language Toolkit
Home-page: https://github.com/awalesushil/yomari
Author: Sushil Awale
Author-email: ssushil.awale@gmail.com
License: MIT
Keywords: language toolkit,nlp,nepali language,newari language
Platform: UNKNOWN
Classifier: License :: OSI Approved :: MIT License
Classifier: Operating System :: OS Independent
Classifier: Programming Language :: Python :: 3
Classifier: Programming Language :: Python :: 3.7
